Metadata-Version: 2.1
Name: gfont
Version: 0.0.3
Summary: 字体解析、ocr 工具
Home-page: https://github.com/Leviathangk/gfont
Author: 郭一会儿
Author-email: 1015295213@qq.com
License: MIT Licence
Keywords: font,font2img,fonttools
Platform: any
